guava_preconditions/__init__.py
guava_preconditions/py.typed
guava_preconditions-0.1.4.dist-info/LICENSE
guava_preconditions-0.1.4.dist-info/WHEEL
guava_preconditions-0.1.4.dist-info/METADATA
guava_preconditions-0.1.4.dist-info/RECORD
