Metadata-Version: 2.1
Name: guava-preconditions
Version: 0.1.4
Summary: A python version of guava's preconditions
Home-page: https://github.com/Mause/guava_preconditions
License: MIT
Author: Elliana
Author-email: me@mause.me
Requires-Python: >=3.6.1
Classifier: License :: OSI Approved :: MIT License
Classifier: Programming Language :: Python :: 3
Classifier: Programming Language :: Python :: 3.7
Classifier: Programming Language :: Python :: 3.8
Classifier: Programming Language :: Python :: 3.9
Project-URL: Repository, https://github.com/Mause/guava_preconditions
